rtl/dma/dma_controller.v
module dma_controller #(
    parameter AXI_ADDR_WIDTH = 32,
    parameter AXI_DATA_WIDTH = 32
) (
    input  wire                  clk,
    input  wire                  rst_n,

    // -- AXI-Lite Slave Interface (CPU -> DMA) --
    input  wire [AXI_ADDR_WIDTH-1:0] s_axi_awaddr,
    input  wire                      s_axi_awvalid,
    output wire                      s_axi_awready,
    input  wire [AXI_DATA_WIDTH-1:0] s_axi_wdata,
    input  wire                      s_axi_wvalid,
    output wire                      s_axi_wready,
    output wire [1:0]                s_axi_bresp,
    output wire                      s_axi_bvalid,
    input  wire                      s_axi_bready,
    input  wire [AXI_ADDR_WIDTH-1:0] s_axi_araddr,
    input  wire                      s_axi_arvalid,
    output wire                      s_axi_arready,
    output wire [AXI_DATA_WIDTH-1:0] s_axi_rdata,
    output wire [1:0]                s_axi_rresp,
    output wire                      s_axi_rvalid,
    input  wire                      s_axi_rready,

    // -- AXI4 Master Interface (DMA -> RAM) --
    output wire [AXI_ADDR_WIDTH-1:0] m_axi_araddr,
    output wire                      m_axi_arvalid,
    input  wire                      m_axi_arready,
    input  wire [AXI_DATA_WIDTH-1:0] m_axi_rdata,
    input  wire [1:0]                m_axi_rresp,
    input  wire                      m_axi_rvalid,
    output wire                      m_axi_rready,
    output wire [AXI_ADDR_WIDTH-1:0] m_axi_awaddr,
    output wire                      m_axi_awvalid,
    input  wire                      m_axi_awready,
    output wire [AXI_DATA_WIDTH-1:0] m_axi_wdata,
    output wire                      m_axi_wvalid,
    input  wire                      m_axi_wready,
    input  wire [1:0]                m_axi_bresp,
    input  wire                      m_axi_bvalid,
    output wire                      m_axi_bready
);

//================================================================
// 1. Thanh ghi nội bộ (Internal Registers)
//================================================================
reg [31:0] reg_src_addr;
reg [31:0] reg_dst_addr;
reg [31:0] reg_len;
reg        reg_start;
reg [1:0]  reg_status; // 00: idle, 01: busy, 10: done

//================================================================
// 2. Logic cho Giao diện Slave (CPU cấu hình DMA)
//================================================================
reg s_axi_awready_reg, s_axi_wready_reg, s_axi_arready_reg, s_axi_rvalid_reg;
reg s_axi_bvalid_reg;

// -- Logic Ghi (Write) --
always @(posedge clk or negedge rst_n) begin
    if (!rst_n) begin
        reg_src_addr <= 32'h0;
        reg_dst_addr <= 32'h0;
        reg_len      <= 32'h0;
        reg_start    <= 1'b0;
        reg_status   <= 2'b00;
    end else begin
        // CPU ghi lệnh vào thanh ghi
        if (s_axi_awvalid && s_axi_wvalid) begin
            case (s_axi_awaddr[3:0])
                4'h0: reg_src_addr <= s_axi_wdata;
                4'h4: reg_dst_addr <= s_axi_wdata;
                4'h8: reg_len      <= s_axi_wdata;
                4'hC: begin
                    reg_start <= s_axi_wdata[0];
                    if (s_axi_wdata[0]) reg_status <= 2'b01; // Set busy
                end
                default: ;
            endcase
        end else begin
            reg_start <= 1'b0; // Start chỉ có hiệu lực 1 chu kỳ
        end
        // Khi DMA làm xong (FSM_DONE), reset lại cờ status
        if(reg_status == 2'b10 && s_axi_bready) reg_status <= 2'b00;
    end
end

assign s_axi_awready = !s_axi_bvalid_reg || s_axi_bready;
assign s_axi_wready  = !s_axi_bvalid_reg || s_axi_bready;
assign s_axi_bvalid  = s_axi_bvalid_reg;
assign s_axi_bresp   = 2'b00; // OK

always @(posedge clk or negedge rst_n) begin
    if (!rst_n) s_axi_bvalid_reg <= 1'b0;
    else if (s_axi_awvalid && s_axi_wvalid && !s_axi_bvalid_reg) s_axi_bvalid_reg <= 1'b1;
    else if (s_axi_bready) s_axi_bvalid_reg <= 1'b0;
end

// -- Logic Đọc (Read - để CPU kiểm tra trạng thái) --
assign s_axi_arready = 1'b1;
assign s_axi_rvalid  = 1'b1;
assign s_axi_rresp   = 2'b00; // OK
assign s_axi_rdata   = (s_axi_araddr[3:0] == 4'hC) ? {30'b0, reg_status} : 32'h0;

//================================================================
// 3. Logic cho Giao diện Master (DMA tự đi làm việc)
//================================================================

// --- Định nghĩa Máy Trạng thái (State Machine) ---
localparam FSM_IDLE       = 3'd0;
localparam FSM_READ_ADDR  = 3'd1;
localparam FSM_READ_DATA  = 3'd2;
localparam FSM_WRITE_ADDR = 3'd3;
localparam FSM_WRITE_DATA = 3'd4;
localparam FSM_WRITE_RESP = 3'd5;

reg [2:0] state, next_state;
reg [31:0] current_src, current_dst, bytes_left;
reg [31:0] data_buffer; // Thanh ghi tạm chứa dữ liệu đã được xử lý

// --- Logic xử lý ảnh (Image Thresholding) ---
wire [31:0] processed_data;
assign processed_data[7:0]   = (m_axi_rdata[7:0]   > 8'd128) ? 8'hFF : 8'h00;
assign processed_data[15:8]  = (m_axi_rdata[15:8]  > 8'd128) ? 8'hFF : 8'h00;
assign processed_data[23:16] = (m_axi_rdata[23:16] > 8'd128) ? 8'hFF : 8'h00;
assign processed_data[31:24] = (m_axi_rdata[31:24] > 8'd128) ? 8'hFF : 8'h00;

// --- Gán tín hiệu điều khiển Master ---
assign m_axi_arvalid = (state == FSM_READ_ADDR);
assign m_axi_araddr  = current_src;
assign m_axi_rready  = (state == FSM_READ_DATA);

assign m_axi_awvalid = (state == FSM_WRITE_ADDR);
assign m_axi_awaddr  = current_dst;
assign m_axi_wvalid  = (state == FSM_WRITE_DATA);
assign m_axi_wdata   = data_buffer;
assign m_axi_bready  = (state == FSM_WRITE_RESP);

// --- Cập nhật trạng thái (Phần Tuần tự) ---
always @(posedge clk or negedge rst_n) begin
    if (!rst_n) begin
        state <= FSM_IDLE;
    end else begin
        state <= next_state;
    end
end

// --- Logic chuyển trạng thái (Phần Tổ hợp) ---
always @(*) begin
    next_state = state;
    case (state)
        FSM_IDLE:
            if (reg_start) begin
                current_src <= reg_src_addr;
                current_dst <= reg_dst_addr;
                bytes_left  <= reg_len;
                next_state  = FSM_READ_ADDR;
            end
        FSM_READ_ADDR:
            if (m_axi_arready) next_state = FSM_READ_DATA;
        FSM_READ_DATA:
            if (m_axi_rvalid) begin
                data_buffer <= processed_data; // Lưu dữ liệu đã qua xử lý
                next_state  = FSM_WRITE_ADDR;
            end
        FSM_WRITE_ADDR:
            if (m_axi_awready) next_state = FSM_WRITE_DATA;
        FSM_WRITE_DATA:
            if (m_axi_wready) next_state = FSM_WRITE_RESP;
        FSM_WRITE_RESP:
            if (m_axi_bvalid) begin
                if (bytes_left <= 4) begin
                    reg_status <= 2'b10; // Đặt cờ báo xong
                    next_state = FSM_IDLE;
                end else begin
                    current_src <= current_src + 4;
                    current_dst <= current_dst + 4;
                    bytes_left  <= bytes_left - 4;
                    next_state  = FSM_READ_ADDR;
                end
            end
        default:
            next_state = FSM_IDLE;
    endcase
end

endmodule

sim/tb_dma.v
`timescale 1ns/1ps

module tb_dma();

    // 1. Khai báo tín hiệu
    reg clk;
    reg rst_n;

    // Tín hiệu AXI-Lite (CPU mô phỏng)
    reg [31:0] s_axi_awaddr;
    reg s_axi_awvalid;
    wire s_axi_awready;
    reg [31:0] s_axi_wdata;
    reg s_axi_wvalid;
    wire s_axi_wready;
    wire [1:0] s_axi_bresp;
    wire s_axi_bvalid;
    reg s_axi_bready;

    // Tín hiệu AXI (RAM mô phỏng)
    wire [31:0] m_axi_araddr;
    wire m_axi_arvalid;
    reg m_axi_arready;
    reg [31:0] m_axi_rdata;
    reg m_axi_rvalid;
    
    wire [31:0] m_axi_awaddr;
    wire m_axi_awvalid;
    reg m_axi_awready;
    wire [31:0] m_axi_wdata;
    wire m_axi_wvalid;
    reg m_axi_wready;
    reg m_axi_bvalid;

    // Kết nối với DMA Controller của bạn
    dma_controller uut (
        .clk(clk), .rst_n(rst_n),
        
        // Slave ports
        .s_axi_awaddr(s_axi_awaddr), .s_axi_awvalid(s_axi_awvalid), .s_axi_awready(s_axi_awready),
        .s_axi_wdata(s_axi_wdata), .s_axi_wvalid(s_axi_wvalid), .s_axi_wready(s_axi_wready),
        .s_axi_bresp(s_axi_bresp), .s_axi_bvalid(s_axi_bvalid), .s_axi_bready(s_axi_bready),
        
        .s_axi_araddr(32'h0), .s_axi_arvalid(1'b0), .s_axi_rready(1'b1), // Bỏ qua phần Read Status cho gọn
        
        // Master ports
        .m_axi_araddr(m_axi_araddr), .m_axi_arvalid(m_axi_arvalid), .m_axi_arready(m_axi_arready),
        .m_axi_rdata(m_axi_rdata), .m_axi_rvalid(m_axi_rvalid), .m_axi_rready(),
        
        .m_axi_awaddr(m_axi_awaddr), .m_axi_awvalid(m_axi_awvalid), .m_axi_awready(m_axi_awready),
        .m_axi_wdata(m_axi_wdata), .m_axi_wvalid(m_axi_wvalid), .m_axi_wready(m_axi_wready),
        .m_axi_bvalid(m_axi_bvalid), .m_axi_bready()
    );

    // 2. Tạo Xung nhịp (Clock) - 10ns
    always #5 clk = ~clk;

    // 3. Khối mô phỏng RAM (Đơn giản hóa)
    reg [31:0] fake_ram [0:1023]; // Bộ nhớ 4KB
    
    always @(posedge clk) begin
        // Phản hồi Đọc
        m_axi_arready <= 1'b1;
        if (m_axi_arvalid && m_axi_arready) begin
            m_axi_rvalid <= 1'b1;
            // Trả về dữ liệu từ RAM. Chú ý: Dịch địa chỉ đi 2 bit (chia 4) vì mỗi ô RAM chứa 4 byte
            m_axi_rdata <= fake_ram[m_axi_araddr >> 2]; 
        end else begin
            m_axi_rvalid <= 1'b0;
        end

        // Phản hồi Ghi
        m_axi_awready <= 1'b1;
        m_axi_wready  <= 1'b1;
        m_axi_bvalid  <= 1'b0;
        if (m_axi_wvalid && m_axi_wready) begin
            fake_ram[m_axi_awaddr >> 2] <= m_axi_wdata; // Ghi dữ liệu vào RAM
            m_axi_bvalid <= 1'b1;
            $display("THỜI GIAN %0t: RAM nhận được dữ liệu GHI: %h tại địa chỉ %h", $time, m_axi_wdata, m_axi_awaddr);
        end
    end

    // 4. Kịch bản chạy Test (CPU)
    initial begin
        // Khởi tạo file xuất waveform để xem trên GTKWave
        $dumpfile("dma_wave.vcd");
        $dumpvars(0, tb_dma);

        // Khởi tạo giá trị
        clk = 0; rst_n = 0;
        s_axi_awvalid = 0; s_axi_wvalid = 0; s_axi_bready = 1;
        
        // Tạo "ảnh gốc" trong RAM (Source Addr = 0x100)
        // Ô thứ 1: Pixel 1=200(Trắng), Pixel 2=50(Đen), Pixel 3=255(Trắng), Pixel 4=10(Đen)
        fake_ram[32'h100 >> 2] = 32'h0A_FF_32_C8; 

        #20 rst_n = 1; // Bỏ Reset
        #20;

        $display("--- BẮT ĐẦU TEST DMA ---");

        // CPU Cấu hình Source = 0x100 (Ghi vào ngăn 0x00)
        s_axi_awaddr = 32'h00; s_axi_wdata = 32'h100;
        s_axi_awvalid = 1; s_axi_wvalid = 1;
        #10 s_axi_awvalid = 0; s_axi_wvalid = 0; #10;

        // CPU Cấu hình Dest = 0x200 (Ghi vào ngăn 0x04)
        s_axi_awaddr = 32'h04; s_axi_wdata = 32'h200;
        s_axi_awvalid = 1; s_axi_wvalid = 1;
        #10 s_axi_awvalid = 0; s_axi_wvalid = 0; #10;

        // CPU Cấu hình Length = 4 bytes (Ghi vào ngăn 0x08)
        s_axi_awaddr = 32'h08; s_axi_wdata = 32'd4;
        s_axi_awvalid = 1; s_axi_wvalid = 1;
        #10 s_axi_awvalid = 0; s_axi_wvalid = 0; #10;

        // CPU Bấm nút START (Ghi 1 vào ngăn 0x0C)
        s_axi_awaddr = 32'h0C; s_axi_wdata = 32'd1;
        s_axi_awvalid = 1; s_axi_wvalid = 1;
        #10 s_axi_awvalid = 0; s_axi_wvalid = 0;

        // Chờ DMA chạy xong
        #200;
        
        $display("--- KẾT THÚC TEST ---");
        $display("Dữ liệu GỐC tại 0x100 : %h", fake_ram[32'h100 >> 2]);
        $display("Dữ liệu ĐÍCH tại 0x200: %h", fake_ram[32'h200 >> 2]);
        
        $finish;
    end
endmodule

sim/dma_wave.vcd
$date
	Mon Apr  6 10:38:00 2026
$end
$version
	Icarus Verilog
$end
$timescale
	1ps
$end
$scope module tb_dma $end
$var wire 2 ! s_axi_bresp [1:0] $end
$var wire 1 " s_axi_wready $end
$var wire 1 # s_axi_bvalid $end
$var wire 1 $ s_axi_awready $end
$var wire 1 % m_axi_wvalid $end
$var wire 32 & m_axi_wdata [31:0] $end
$var wire 1 ' m_axi_awvalid $end
$var wire 32 ( m_axi_awaddr [31:0] $end
$var wire 1 ) m_axi_arvalid $end
$var wire 32 * m_axi_araddr [31:0] $end
$var reg 1 + clk $end
$var reg 1 , m_axi_arready $end
$var reg 1 - m_axi_awready $end
$var reg 1 . m_axi_bvalid $end
$var reg 32 / m_axi_rdata [31:0] $end
$var reg 1 0 m_axi_rvalid $end
$var reg 1 1 m_axi_wready $end
$var reg 1 2 rst_n $end
$var reg 32 3 s_axi_awaddr [31:0] $end
$var reg 1 4 s_axi_awvalid $end
$var reg 1 5 s_axi_bready $end
$var reg 32 6 s_axi_wdata [31:0] $end
$var reg 1 7 s_axi_wvalid $end
$scope module uut $end
$var wire 1 + clk $end
$var wire 32 8 m_axi_araddr [31:0] $end
$var wire 1 , m_axi_arready $end
$var wire 32 9 m_axi_awaddr [31:0] $end
$var wire 1 - m_axi_awready $end
$var wire 2 : m_axi_bresp [1:0] $end
$var wire 1 . m_axi_bvalid $end
$var wire 32 ; m_axi_rdata [31:0] $end
$var wire 2 < m_axi_rresp [1:0] $end
$var wire 1 0 m_axi_rvalid $end
$var wire 32 = m_axi_wdata [31:0] $end
$var wire 1 1 m_axi_wready $end
$var wire 1 2 rst_n $end
$var wire 32 > s_axi_araddr [31:0] $end
$var wire 1 ? s_axi_arready $end
$var wire 1 @ s_axi_arvalid $end
$var wire 32 A s_axi_awaddr [31:0] $end
$var wire 1 $ s_axi_awready $end
$var wire 1 4 s_axi_awvalid $end
$var wire 1 5 s_axi_bready $end
$var wire 2 B s_axi_bresp [1:0] $end
$var wire 1 # s_axi_bvalid $end
$var wire 1 C s_axi_rready $end
$var wire 2 D s_axi_rresp [1:0] $end
$var wire 1 E s_axi_rvalid $end
$var wire 32 F s_axi_wdata [31:0] $end
$var wire 1 " s_axi_wready $end
$var wire 1 7 s_axi_wvalid $end
$var wire 32 G s_axi_rdata [31:0] $end
$var wire 32 H processed_data [31:0] $end
$var wire 1 % m_axi_wvalid $end
$var wire 1 I m_axi_rready $end
$var wire 1 J m_axi_bready $end
$var wire 1 ' m_axi_awvalid $end
$var wire 1 ) m_axi_arvalid $end
$var parameter 32 K AXI_ADDR_WIDTH $end
$var parameter 32 L AXI_DATA_WIDTH $end
$var parameter 3 M FSM_IDLE $end
$var parameter 3 N FSM_READ_ADDR $end
$var parameter 3 O FSM_READ_DATA $end
$var parameter 3 P FSM_WRITE_ADDR $end
$var parameter 3 Q FSM_WRITE_DATA $end
$var parameter 3 R FSM_WRITE_RESP $end
$var reg 32 S bytes_left [31:0] $end
$var reg 32 T current_dst [31:0] $end
$var reg 32 U current_src [31:0] $end
$var reg 32 V data_buffer [31:0] $end
$var reg 3 W next_state [2:0] $end
$var reg 32 X reg_dst_addr [31:0] $end
$var reg 32 Y reg_len [31:0] $end
$var reg 32 Z reg_src_addr [31:0] $end
$var reg 1 [ reg_start $end
$var reg 2 \ reg_status [1:0] $end
$var reg 1 ] s_axi_bvalid_reg $end
$var reg 3 ^ state [2:0] $end
$upscope $end
$upscope $end
$enddefinitions $end
$comment Show the parameter values. $end
$dumpall
b101 R
b100 Q
b11 P
b10 O
b1 N
b0 M
b100000 L
b100000 K
$end
#0
$dumpvars
b0 ^
0]
b0 \
0[
b0 Z
b0 Y
b0 X
b0 W
bx V
bx U
bx T
bx S
0J
0I
bx H
b0 G
bx F
1E
b0 D
1C
b0 B
bx A
0@
1?
b0 >
bx =
bz <
bx ;
bz :
bx 9
bx 8
07
bx 6
15
04
bx 3
02
x1
x0
bx /
x.
x-
x,
0+
bx *
0)
bx (
0'
bx &
0%
1$
0#
1"
b0 !
$end
#5000
0.
11
1-
00
1,
1+
#10000
0+
#15000
1+
#20000
0+
12
#25000
1+
#30000
0+
#35000
1+
#40000
0+
17
14
b100000000 6
b100000000 F
b0 3
b0 A
#45000
1#
1]
b100000000 Z
1+
#50000
0+
07
04
#55000
0#
0]
1+
#60000
0+
17
14
b1000000000 6
b1000000000 F
b100 3
b100 A
#65000
1#
1]
b1000000000 X
1+
#70000
0+
07
04
#75000
0#
0]
1+
#80000
0+
17
14
b100 6
b100 F
b1000 3
b1000 A
#85000
1#
1]
b100 Y
1+
#90000
0+
07
04
#95000
0#
0]
1+
#100000
0+
17
14
b1 6
b1 F
b1100 3
b1100 A
#105000
b100 S
b1000000000 (
b1000000000 9
b1000000000 T
b100000000 *
b100000000 8
b100000000 U
b1 W
1#
1]
b1 \
1[
1+
#110000
0+
07
04
#115000
b10 W
0[
0#
0]
1)
b1 ^
1+
#120000
0+
#125000
b111111110000000011111111 &
b111111110000000011111111 =
b111111110000000011111111 V
b111111110000000011111111 H
b11 W
0)
1I
b10 ^
b1010111111110011001011001000 /
b1010111111110011001011001000 ;
10
1+
#130000
0+
#135000
b100 W
0I
1'
b11 ^
00
1+
#140000
0+
#145000
b101 W
0'
1%
b100 ^
1+
#150000
0+
#155000
b10 \
b0 W
0%
1J
b101 ^
1.
1+
#160000
0+
#165000
0J
b0 ^
b0 \
0.
1+
